pyfiber/__init__.py
pyfiber/_utils.py
pyfiber/analysis.py
pyfiber/behavior.py
pyfiber/fiber.py
pyfiber/pyfiber.yaml
pyfiber-0.2.16.dist-info/LICENSE
pyfiber-0.2.16.dist-info/METADATA
pyfiber-0.2.16.dist-info/WHEEL
pyfiber-0.2.16.dist-info/top_level.txt
pyfiber-0.2.16.dist-info/RECORD
