Metadata-Version: 2.2
Name: pyfiber
Version: 0.2.16
Summary: Fiber photometry and behavioral data analysis tool
Home-page: https://github.com/matias-ceau/pyfiber
Author: Matias Ceau
Author-email: matias@ceau.net
License: GPLv3
Keywords: fiber photometry,operant behavior
Classifier: Development Status :: 4 - Beta
Classifier: Programming Language :: Python :: 3
Classifier: Programming Language :: Python :: 3 :: Only
Classifier: License :: OSI Approved :: GNU General Public License v3 or later (GPLv3+)
Classifier: Operating System :: Microsoft :: Windows
Classifier: Operating System :: POSIX
Classifier: Operating System :: Unix
Classifier: Operating System :: MacOS
Classifier: Topic :: Scientific/Engineering
Classifier: Intended Audience :: Science/Research
Classifier: Intended Audience :: Developers
License-File: LICENSE
Requires-Dist: numpy
Requires-Dist: scipy
Requires-Dist: pandas
Requires-Dist: pyyaml
Requires-Dist: datetime
Requires-Dist: seaborn
Requires-Dist: matplotlib
Requires-Dist: portion
Requires-Dist: h5py
Dynamic: author
Dynamic: author-email
Dynamic: classifier
Dynamic: description
Dynamic: description-content-type
Dynamic: home-page
Dynamic: keywords
Dynamic: license
Dynamic: requires-dist
Dynamic: summary
